pyyaml_loaders/IgnoreLoader.py
pyyaml_loaders/IncludeLoader.py
pyyaml_loaders/__init__.py
pyyaml_loaders-0.2.0.dist-info/licenses/LICENSE
pyyaml_loaders-0.2.0.dist-info/METADATA
pyyaml_loaders-0.2.0.dist-info/WHEEL
pyyaml_loaders-0.2.0.dist-info/top_level.txt
pyyaml_loaders-0.2.0.dist-info/RECORD
