Metadata-Version: 2.4
Name: pyyaml-loaders
Version: 0.2.0
Summary: PyYAML loaders with enhanced functionalities.
Author-email: François De Keersmaeker <francois.dekeersmaeker+github@proton.me>
Maintainer-email: François De Keersmaeker <francois.dekeersmaeker+github@proton.me>
License-Expression: GPL-3.0-or-later
Project-URL: Homepage, https://github.com/smart-home-network-security/pyyaml-loaders
Project-URL: Source, https://github.com/smart-home-network-security/pyyaml-loaders
Keywords: yaml,pyyaml
Classifier: Development Status :: 3 - Alpha
Classifier: Programming Language :: Python :: 3
Classifier: Programming Language :: Python :: 3.8
Classifier: Programming Language :: Python :: 3.9
Classifier: Programming Language :: Python :: 3.10
Classifier: Programming Language :: Python :: 3.11
Classifier: Programming Language :: Python :: 3.12
Classifier: Programming Language :: Python :: 3 :: Only
Classifier: Operating System :: OS Independent
Requires-Python: >=3.8
License-File: LICENSE
Requires-Dist: PyYAML
Dynamic: license-file
